[
    {
        "name": "anting-anting dan subang emas",
        "value": "anting_dan_subang",
        "kategori": ""
    },

    {
        "name": "choker",
        "value": "choker",
        "kategori": ""
    },
    {
        "name": "cincin belah rotan",
        "value": "cincin_belah_rotan",
        "kategori": "cincin"
    },
    {
        "name": "cincin emas",
        "value": "cincin_emas",
        "kategori": "cincin"
    },
    {
        "name": "cincin emas permata",
        "value": "cincin_emas_permata",
        "kategori": "cincin"
    },
    {
        "name": "cincin perak",
        "value": "cincin_perak",
        "kategori": "cincin"
    },
    {
        "name": "gelang emas",
        "value": "gelang_emas",
        "kategori": ""
    },
    {
        "name": "koleksi kanak kanak",
        "value": "koleksi_kanak_kanak",
        "kategori": ""
    },
    {
        "name": "loket emas",
        "value": "loket_emas",
        "kategori": ""
    },
    {
        "name": "rantai kaki",
        "value": "rantai_kaki",
        "kategori": ""
    },
    {
        "name": "rantai leher",
        "value": "rantai_leher",
        "kategori": ""
    },
    {
        "name": "rantai tangan fesyen",
        "value": "rantai_tangan_fesyen",
        "kategori": ""
    },
    {
        "name": "rantai tangan gantung",
        "value": "rantai_tangan_gantung",
        "kategori": ""
    },
    {
        "name": "rantai tangan kosong",
        "value": "rantai_tangan_kosong",
        "kategori": ""
    },
    {
        "name": "rantai tangan padu",
        "value": "rantai_tangan_padu"
    }
]
